restoration/__init__.py
restoration/cli.py
restoration/parser.py
restoration-0.2.1.dist-info/LICENSE
restoration-0.2.1.dist-info/METADATA
restoration-0.2.1.dist-info/WHEEL
restoration-0.2.1.dist-info/entry_points.txt
restoration-0.2.1.dist-info/top_level.txt
restoration-0.2.1.dist-info/RECORD
