Metadata-Version: 2.1
Name: restoration
Version: 0.2.1
Summary: A parser for Age of Mythology .mythrec files
Author-email: Jeremy Keeler <jeremy@keeler.dev>
License: Copyright (c) 2025 jeremy@keeler.dev
Project-URL: repository, https://github.com/jerkeeler/restoration
Project-URL: homepage, https://github.com/jerkeeler/restoration
Project-URL: issues, https://github.com/jerkeeler/restoration/issues
Project-URL: changelog, https://github.com/jerkeeler/restoration/blob/master/CHANGELOG.md
Classifier: Programming Language :: Python :: 3
Classifier: License :: OSI Approved :: MIT License
Classifier: Operating System :: OS Independent
License-File: LICENSE
Requires-Dist: click>=8.0.0
Provides-Extra: dev
Requires-Dist: black>=24.10.0; extra == "dev"
Requires-Dist: isort>=5.13.2; extra == "dev"
Requires-Dist: mypy>=1.14.1; extra == "dev"
Requires-Dist: pre-commit>=4.0.1; extra == "dev"
Requires-Dist: pytest>=8.3.4; extra == "dev"
